govtech_csg_xcg/secretsmanager/__init__.py
govtech_csg_xcg/secretsmanager/clients.py
govtech_csg_xcg/secretsmanager/middleware.py
govtech_csg_xcg/secretsmanager/db/__init__.py
govtech_csg_xcg/secretsmanager/db/common.py
govtech_csg_xcg/secretsmanager/db/mysql/__init__.py
govtech_csg_xcg/secretsmanager/db/mysql/base.py
govtech_csg_xcg/secretsmanager/db/postgresql/__init__.py
govtech_csg_xcg/secretsmanager/db/postgresql/base.py
govtech_csg_xcg_secretsmanager-0.1.0.dist-info/LICENSE
govtech_csg_xcg_secretsmanager-0.1.0.dist-info/METADATA
govtech_csg_xcg_secretsmanager-0.1.0.dist-info/WHEEL
govtech_csg_xcg_secretsmanager-0.1.0.dist-info/top_level.txt
govtech_csg_xcg_secretsmanager-0.1.0.dist-info/RECORD
