Metadata-Version: 2.1
Name: govtech-csg-xcg-secretsmanager
Version: 0.1.0
Summary: Package containing functionality related to secrets management using AWS Secrets Manager.
Project-URL: Homepage, https://xcg.tech.gov.sg
Project-URL: Documentation, https://xcg.tech.gov.sg
Project-URL: Repository, https://github.com/GovTech-CSG/govtech-csg-xcg-secretsmanager
Classifier: Development Status :: 4 - Beta
Classifier: License :: OSI Approved :: Mozilla Public License 2.0 (MPL 2.0)
Requires-Python: >=3.8
License-File: LICENSE
Requires-Dist: django ~=4.1
Requires-Dist: boto3
Requires-Dist: aws-secretsmanager-caching ~=1.1.1.5
Provides-Extra: mysql
Requires-Dist: mysqlclient ~=1.4.0 ; extra == 'mysql'
Provides-Extra: postgresql
Requires-Dist: psycopg2 ~=2.8.4 ; extra == 'postgresql'
